setup.py
dnsyo/__init__.py
dnsyo/cli.py
dnsyo/dnsyo.py
dnsyo/updater.py
dnsyo.egg-info/PKG-INFO
dnsyo.egg-info/SOURCES.txt
dnsyo.egg-info/dependency_links.txt
dnsyo.egg-info/entry_points.txt
dnsyo.egg-info/requires.txt
dnsyo.egg-info/top_level.txt
dnsyo.egg-info/zip-safe