Metadata-Version: 1.1
Name: dnsyo
Version: 2.0.6
Summary: Query over 1500 global DNS servers and colate their results. Track the propagation of your domains around the world.
Home-page: https://github.com/samarudge/dnsyo
Author: Sam Rudge
Author-email: sam@codesam.co.uk
License: https://raw.github.com/samarudge/dnsyo/master/LICENCE.txt
Platform: UNKNOWN
Classifier: Environment :: Console
Classifier: Intended Audience :: Developers
Classifier: Intended Audience :: System Administrators
Classifier: License :: OSI Approved :: MIT License
Classifier: Topic :: Internet :: Name Service (DNS)
